kaiju_adb_lib/__init__.py
kaiju_adb_lib/__main__.py
kaiju_adb_lib/client.py
kaiju_adb_lib/retry_with_backoff.py
kaiju_adb_lib/support.py
kaiju_adb_lib-1.7.3.dist-info/METADATA
kaiju_adb_lib-1.7.3.dist-info/WHEEL
kaiju_adb_lib-1.7.3.dist-info/dependency_links.txt
kaiju_adb_lib-1.7.3.dist-info/entry_points.txt
kaiju_adb_lib-1.7.3.dist-info/top_level.txt
kaiju_adb_lib-1.7.3.dist-info/RECORD
